[{"c":"Qaanaaq","i":"NAQ","p":"Groenlandia","y":"GL"},{"c":"Qaarsut","i":"JQA","p":"Groenlandia","y":"GL"},{"c":"Qachas Nek","i":"UNE","p":"Lesotho","y":"LS"},{"c":"Qaisumah","i":"AQI","p":"Arabia Saudí","y":"SA"},{"c":"Qala Nau","i":"LQN","p":"Afganistán","y":"AF"},{"c":"Qaqortoq","i":"JJU","p":"Groenlandia","y":"GL"},{"c":"Qasigiannguit","i":"JCH","p":"Groenlandia","y":"GL"},{"c":"Qassiarsuk","i":"QFT","p":"Groenlandia","y":"GL"},{"c":"Qatif","i":"QTF","p":"Arabia Saudí","y":"SA"},{"c":"Qeqertarsuaq","i":"JGO","p":"Groenlandia","y":"GL"},{"c":"Qeqertarsuatsiaat","i":"QEY","p":"Groenlandia","y":"GL"},{"c":"Qiemo","i":"IQM","p":"China","y":"CN"},{"c":"Qingdao","i":"TAO","p":"China","y":"CN"},{"c":"Qingyang","i":"IQN","p":"China","y":"CN"},{"c":"Qinhuangdao","i":"SHP","p":"China","y":"CN"},{"c":"Qiqihar","i":"NDG","p":"China","y":"CN"},{"c":"Qish","i":"IHN","p":"Yemén","y":"YE"},{"c":"Qom","i":"QUM","p":"Irán","y":"IR"},{"c":"Qom","i":"XQO","p":"Irán","y":"IR"},{"c":"Quakertown","i":"UKT","p":"Estados Unidos","y":"US"},{"c":"Qualicum","i":"XQU","p":"Canadá","y":"CA"},{"c":"Quanduc","i":"HOO","p":"Vietnam","y":"VN"},{"c":"Quang Ngai","i":"XNG","p":"Vietnam","y":"VN"},{"c":"Quantico","i":"NYG","p":"Estados Unidos","y":"US"},{"c":"Quaqtaq","i":"YQC","p":"Canadá","y":"CA"},{"c":"Quebec","i":"YQB","p":"Canadá","y":"CA"},{"c":"Queen","i":"UQE","p":"Estados Unidos","y":"US"},{"c":"Queen Charlotte Is","i":"ZQS","p":"Canadá","y":"CA"},{"c":"Queenstown","i":"ZQN","p":"Nueva Zelanda","y":"NZ"},{"c":"Queenstown","i":"UEE","p":"Australia","y":"AU"},{"c":"Queenstown","i":"UTW","p":"Sudáfrica","y":"ZA"},{"c":"Quelimane","i":"UEL","p":"Mozambique","y":"MZ"},{"c":"Quepos","i":"XQP","p":"Costa Rica","y":"CR"},{"c":"Queretaro","i":"QRO","p":"México","y":"MX"},{"c":"Quesnel","i":"YQZ","p":"Canadá","y":"CA"},{"c":"Quetta","i":"UET","p":"Pakistán","y":"PK"},{"c":"Quetzaltenango","i":"AAZ","p":"Guatemala","y":"GT"},{"c":"Qui Nhon","i":"UIH","p":"Vietnam","y":"VN"},{"c":"Quibdo","i":"UIB","p":"Colombia","y":"CO"},{"c":"Quiche","i":"AQB","p":"Guatemala","y":"GT"},{"c":"Quillayute","i":"UIL","p":"Estados Unidos","y":"US"},{"c":"Quilpie","i":"ULP","p":"Australia","y":"AU"},{"c":"Quimper","i":"UIP","p":"Francia","y":"FR"},{"c":"Quincemil","i":"UMI","p":"Perú","y":"PE"},{"c":"Quincy","i":"UIN","p":"Estados Unidos","y":"US"},{"c":"Quincy","i":"MQI","p":"Estados Unidos","y":"US"},{"c":"Quine Hill","i":"UIQ","p":"Vanuatu","y":"VU"},{"c":"Quinhagak","i":"KWN","p":"Estados Unidos","y":"US"},{"c":"Quirindi","i":"UIR","p":"Australia","y":"AU"},{"c":"Quito","i":"UIO","p":"Ecuador","y":"EC"},{"c":"Quixada","i":"QIX","p":"Brasil","y":"BR"},{"c":"Qullissat","i":"QUE","p":"Groenlandia","y":"GL"},{"c":"Quonset Point","i":"NCO","p":"Estados Unidos","y":"US"},{"c":"Qurghonteppa","i":"KQT","p":"Tayikistán","y":"TJ"},{"c":"Quthing","i":"UTG","p":"Lesotho","y":"LS"}]
